agenv/__init__.py
agenv/decrypt.py
agenv-0.5.0.dist-info/licenses/LICENSE
tests/__init__.py
tests/test_decrypt.py
agenv-0.5.0.dist-info/METADATA
agenv-0.5.0.dist-info/WHEEL
agenv-0.5.0.dist-info/top_level.txt
agenv-0.5.0.dist-info/RECORD
