Metadata-Version: 2.4
Name: agenv
Version: 0.5.0
Summary: Load environment variables from age-encrypted files
Author-email: Zach Cheung <kuroro.zhang@gmail.com>
License: MIT
Project-URL: Homepage, https://github.com/zachcheung/agenv
Requires-Python: >=3.7
License-File: LICENSE
Provides-Extra: dotenv
Requires-Dist: python-dotenv; extra == "dotenv"
Dynamic: license-file
